ferrocene_intersphinx_builder.py
ferrocene_standalone_make_cli.py
ferrocene_toctrees.py
ferrocene_autoglossary/__init__.py
ferrocene_autoglossary/debug.py
ferrocene_autoglossary/lexer.py
ferrocene_domain_cli/__init__.py
ferrocene_domain_cli/domain.py
ferrocene_domain_cli/traceability_ids.py
ferrocene_qualification/__init__.py
ferrocene_qualification/document_id.py
ferrocene_qualification/domain.py
ferrocene_qualification/intersphinx_support.py
ferrocene_qualification/signature_page.py
ferrocene_qualification/sphinx_needs_support.py
ferrocene_qualification/substitutions.py
ferrocene_qualification/target.py
ferrocene_qualification/upcoming.py
ferrocene_qualification/signature_page/breadcrumbs.js
ferrocene_qualification/signature_page/template.html
ferrocene_theme/__init__.py
ferrocene_theme/fontawesome.html
ferrocene_theme/layout.html
ferrocene_theme/search.html
ferrocene_theme/theme.toml
ferrocene_theme/static/favicon.svg
ferrocene_theme/static/ferrocene.css
ferrocene_theme/static/ferrocene.svg
ferrocene_theme/static/fonts/raleway-400-italic.ttf
ferrocene_theme/static/fonts/raleway-400-italic.ttf.license
ferrocene_theme/static/fonts/raleway-400-italic.woff2
ferrocene_theme/static/fonts/raleway-400-italic.woff2.license
ferrocene_theme/static/fonts/raleway-400.ttf
ferrocene_theme/static/fonts/raleway-400.ttf.license
ferrocene_theme/static/fonts/raleway-400.woff2
ferrocene_theme/static/fonts/raleway-400.woff2.license
ferrocene_theme/static/fonts/raleway-700-italic.ttf
ferrocene_theme/static/fonts/raleway-700-italic.ttf.license
ferrocene_theme/static/fonts/raleway-700-italic.woff2
ferrocene_theme/static/fonts/raleway-700-italic.woff2.license
ferrocene_theme/static/fonts/raleway-700.ttf
ferrocene_theme/static/fonts/raleway-700.ttf.license
ferrocene_theme/static/fonts/raleway-700.woff2
ferrocene_theme/static/fonts/raleway-700.woff2.license
ferrocene_theme/static/fonts/roboto-mono-400-italic.ttf
ferrocene_theme/static/fonts/roboto-mono-400-italic.ttf.license
ferrocene_sphinx_shared_resources-0.0.4.dist-info/METADATA
ferrocene_sphinx_shared_resources-0.0.4.dist-info/WHEEL
ferrocene_sphinx_shared_resources-0.0.4.dist-info/entry_points.txt
ferrocene_sphinx_shared_resources-0.0.4.dist-info/RECORD
