Metadata-Version: 2.4
Name: ferrocene-sphinx-shared-resources
Version: 0.0.4
Summary: Internal resources used for Ferrocene's Sphinx documentation
License-Expression: MIT OR Apache-2.0
Requires-Python: >=3.10
Requires-Dist: sphinx~=8.0
Requires-Dist: tomli~=2.2
